dendritex/__init__.py
dendritex/_base.py
dendritex/_base_test.py
dendritex/_integrators.py
dendritex/_misc.py
dendritex/_protocol.py
dendritex/channels/__init__.py
dendritex/channels/calcium.py
dendritex/channels/hyperpolarization_activated.py
dendritex/channels/leaky.py
dendritex/channels/potassium.py
dendritex/channels/potassium_calcium.py
dendritex/channels/sodium.py
dendritex/ions/__init__.py
dendritex/ions/calcium.py
dendritex/ions/potassium.py
dendritex/ions/sodium.py
dendritex/neurons/__init__.py
dendritex/neurons/multi_compartment.py
dendritex/neurons/single_compartment.py
dendritex-0.0.1.post20250203.dist-info/LICENSE
dendritex-0.0.1.post20250203.dist-info/METADATA
dendritex-0.0.1.post20250203.dist-info/WHEEL
dendritex-0.0.1.post20250203.dist-info/top_level.txt
dendritex-0.0.1.post20250203.dist-info/RECORD
