Metadata-Version: 2.1
Name: dendritex
Version: 0.0.1.post20250203
Summary: Dendrite Modeling in Python
Home-page: https://github.com/chaobrain/dendritex
Author: Dendritex Developers
Author-email: dendritex Developers <chao.brain@qq.com>
License: Apache-2.0 license
Project-URL: homepage, http://github.com/chaobrain/dendritex
Project-URL: repository, http://github.com/chaobrain/dendritex
Keywords: dendritic computation,dendritic modeling,brain modeling,neuron simulation
Classifier: Natural Language :: English
Classifier: Operating System :: OS Independent
Classifier: Development Status :: 4 - Beta
Classifier: Intended Audience :: Developers
Classifier: Intended Audience :: Science/Research
Classifier: Programming Language :: Python :: 3
Classifier: Programming Language :: Python :: 3.9
Classifier: Programming Language :: Python :: 3.10
Classifier: Programming Language :: Python :: 3.11
Classifier: Programming Language :: Python :: 3.12
Classifier: License :: OSI Approved :: Apache Software License
Classifier: Programming Language :: Python
Classifier: Topic :: Scientific/Engineering :: Bio-Informatics
Classifier: Topic :: Scientific/Engineering :: Mathematics
Classifier: Topic :: Scientific/Engineering :: Artificial Intelligence
Classifier: Topic :: Software Development :: Libraries
Requires-Python: >=3.9
License-File: LICENSE
Requires-Dist: jax
Requires-Dist: jaxlib
Requires-Dist: numpy
Requires-Dist: brainstate (>=0.1.0)
Requires-Dist: brainunit (>=0.0.2.post20240903)
Provides-Extra: cpu
Requires-Dist: jaxlib ; extra == 'cpu'
Provides-Extra: cuda12
Requires-Dist: jaxlib[cuda12] ; extra == 'cuda12'
Provides-Extra: testing
Requires-Dist: pytest ; extra == 'testing'
Provides-Extra: tpu
Requires-Dist: jaxlib[tpu] ; extra == 'tpu'
